gitks/__init__.py
gitks/py.typed
gitks/cli/__init__.py
gitks/cli/__main__.py
gitks/core/__init__.py
gitks-0.0.0.dev1.dist-info/licenses/LICENSE
gitks-0.0.0.dev1.dist-info/METADATA
gitks-0.0.0.dev1.dist-info/WHEEL
gitks-0.0.0.dev1.dist-info/entry_points.txt
gitks-0.0.0.dev1.dist-info/top_level.txt
gitks-0.0.0.dev1.dist-info/RECORD
